sphinxcontrib.constdata-1.0.11-py3.8-nspkg.pth
sphinxcontrib/constdata/__init__.py
sphinxcontrib/constdata/domain.py
sphinxcontrib/constdata/flatfiles.py
sphinxcontrib/constdata/l10n.py
sphinxcontrib/constdata/label_role.py
sphinxcontrib/constdata/link_role.py
sphinxcontrib/constdata/settings.py
sphinxcontrib/constdata/table_directive.py
sphinxcontrib/constdata/templating.py
sphinxcontrib/constdata/url.py
sphinxcontrib/constdata/utils.py
sphinxcontrib.constdata-1.0.11.dist-info/AUTHORS
sphinxcontrib.constdata-1.0.11.dist-info/LICENSE
sphinxcontrib.constdata-1.0.11.dist-info/METADATA
sphinxcontrib.constdata-1.0.11.dist-info/WHEEL
sphinxcontrib.constdata-1.0.11.dist-info/namespace_packages.txt
sphinxcontrib.constdata-1.0.11.dist-info/pbr.json
sphinxcontrib.constdata-1.0.11.dist-info/top_level.txt
sphinxcontrib.constdata-1.0.11.dist-info/RECORD
