Metadata-Version: 2.1
Name: sphinxcontrib.constdata
Version: 1.0.11
Summary: Sphinx extension that allows showing values, tables, and links from CSV files. Instead of hard-coding values in the text, you write constants or queries replaced with value(s) from the CSV file. If the file contains language-depending strings, they can be translated with the rest of the Sphinx docs.
Home-page: https://gitlab.com/documatt/sphinxcontrib-constdata
Author: Documatt s.r.o.
Author-email: documatt@documatt.com
License: UNKNOWN
Platform: UNKNOWN
Classifier: Environment :: Console
Classifier: Environment :: Web Environment
Classifier: Framework :: Sphinx :: Extension
Classifier: Intended Audience :: Developers
Classifier: License :: OSI Approved :: BSD License
Classifier: Operating System :: OS Independent
Classifier: Programming Language :: Python
Classifier: Programming Language :: Python :: 3
Classifier: Programming Language :: Python :: 3.6
Classifier: Programming Language :: Python :: 3.7
Classifier: Programming Language :: Python :: 3.8
Classifier: Programming Language :: Python :: 3.9
Classifier: Topic :: Documentation
Classifier: Topic :: Documentation :: Sphinx
Classifier: Topic :: Utilities
License-File: LICENSE
License-File: AUTHORS
Requires-Dist: pbr (==5.8.0)
Requires-Dist: Sphinx
Requires-Dist: pyaml (==21.10.1)
